README.md
setup.py
gt_tsp/__init__.py
gt_tsp/held_karp.py
gt_tsp/naive.py
gt_tsp/utils.py
gt_tsp.egg-info/PKG-INFO
gt_tsp.egg-info/SOURCES.txt
gt_tsp.egg-info/dependency_links.txt
gt_tsp.egg-info/top_level.txt
gt_tsp.egg-info/zip-safe