Metadata-Version: 1.0
Name: gt-tsp
Version: 1.0.0
Summary: Traveling Salesperson Problem - Solutions in Python
Home-page: https://github.com/p13i/Traveling-Salesman-Problem
Author: Pramod Kotipalli - School of Interactive Computing - Georgia Institute of Technology
Author-email: pramodk@gatech.edu
License: UNKNOWN
Platform: UNKNOWN
